MANIFEST.in
README.md
setup.py
pyqa/__init__.py
pyqa/pyqa.py
pyqa/questions.py
pyqa.egg-info/PKG-INFO
pyqa.egg-info/SOURCES.txt
pyqa.egg-info/dependency_links.txt
pyqa.egg-info/requires.txt
pyqa.egg-info/top_level.txt