Metadata-Version: 1.0
Name: pyqa
Version: 0.6.1
Summary: pyqa makes it easy to write conversational scripts that generate configuration
Home-page: http://github.com/bebraw/pyqa
Author: Juho Vepsäläinen
Author-email: bebraw@gmail.com
License: MIT
Keywords: scripting,utility,configuration
Platform: UNKNOWN
Classifier: Development Status :: 4 - Beta
Classifier: Intended Audience :: Developers
Classifier: License :: OSI Approved :: MIT License
Classifier: Natural Language :: English
Classifier: Operating System :: OS Independent
Classifier: Programming Language :: Python
Classifier: Topic :: Scientific/Engineering
Classifier: Topic :: Software Development
